<?xml version='1.0' encoding='utf-8'?>
<data>
  <cars><car>
			<mark_id>Livan</mark_id>
			<folder_id>S6 Pro</folder_id>
			<modification_id>1.5 AMT (147 л.с.)</modification_id>
			<body_type>Седан</body_type>
			<complectation_name>Premium</complectation_name>
			<wheel>левый</wheel>
			<color>Серый</color>
			<metallic>нет</metallic>
			<availability>в наличии</availability>
			<custom>растаможен</custom>
			<owners_number>Не было владельцев</owners_number>
			<year>2023</year>
			<price>2649900</price>
			<credit_discount>0</credit_discount>
			<insurance_discount>0</insurance_discount>
			<tradein_discount>0</tradein_discount>
			<optional_discount>0</optional_discount>
			<currency>RUR</currency>
			<registry_year>2023</registry_year>
			<vin>LLV2A3B20P0300587</vin>
			<description>Livan-суббренд GEELY, это значит, что схема производства, цепочка поставки компонентов, стандарты и уровень качества продукции высшего уровня.
Автомобиль пpедставлeн официaльным дилером Livan в г. Самара В нашем автосалоне для вас: Большой выбор автомобилей Livan в наличии Выгодный обмен по программе Тrаdе-in Большой выбор автомобилей с пробегом Выкуп автомобилей Официальный сервисный центр Кузовной сервис Кредит на выгодных условиях Страхование КАСКО, ОСАГО
Максимальная выгода указана с учетом всех предоставляемых скидок, при условии покупки автомобиля в кредит и  при участии  в программе Тrаdе-in
Авторассрочка:12,24,36 мес. Лизинг (для юридических лиц) Дополнительное оборудование Стоимость указана с учетом скидок и предложений Мы рады видеть Вас ежедневно с 08:00 до 20:00 по адресу: Самара, Ново-Урицкая 22А.</description>
			<images>
				<image>https://cars.avto-provereno.ru/feeds//LLV2A3B20P0300587/5fe2a7d5ca58500cdced986997e336c8.jpg</image>
				<image>https://cars.avto-provereno.ru/feeds//LLV2A3B20P0300587/dd42717ce61e0b2e4ea70031e4ca9c23.jpg</image>
				<image>https://cars.avto-provereno.ru/feeds//LLV2A3B20P0300587/517bc11ce624b39f731e54fefbe503ab.jpg</image>
				<image>https://cars.avto-provereno.ru/feeds//LLV2A3B20P0300587/e5262370ac5d1376a42f14bfd387c7c6.jpg</image>
				<image>https://cars.avto-provereno.ru/feeds//LLV2A3B20P0300587/c58f888b5d8244181b01f21fe7ebf787.jpg</image>
				<image>https://cars.avto-provereno.ru/feeds//LLV2A3B20P0300587/9a75d14d47f37a939425ebac0067c9bc.jpg</image>
				<image>https://cars.avto-provereno.ru/feeds//LLV2A3B20P0300587/acfb5d2aa8221fc2ef940fd30285f735.jpg</image>
				<image>https://cars.avto-provereno.ru/feeds//LLV2A3B20P0300587/f8c1b426454e6817195c9aee17f3b4fd.jpg</image>
			</images>
		<max_discount>993900</max_discount><priceWithDiscount>1656000</priceWithDiscount><sale_price>1656000</sale_price><url>https://livan-samara.ru/cars/livan-s6-pro-15-amt-147-лс-premium-серый-2023/</url></car>
		<car>
			<mark_id>Livan</mark_id>
			<folder_id>X3 Pro</folder_id>
			<modification_id>1.5 CVT (103 л.с.)</modification_id>
			<body_type>Внедорожник 5 дв.</body_type>
			<complectation_name>Luxury</complectation_name>
			<wheel>левый</wheel>
			<color>БЕЖЕВЫЙ</color>
			<metallic>да</metallic>
			<availability>в наличии</availability>
			<custom>растаможен</custom>
			<owners_number>Не было владельцев</owners_number>
			<year>2023</year>
			<price>1899900</price>
			<credit_discount>120000</credit_discount>
			<insurance_discount>0</insurance_discount>
			<tradein_discount>100000</tradein_discount>
			<optional_discount>0</optional_discount>
			<currency>RUR</currency>
			<registry_year>2023</registry_year>
			<vin>LLV2C3B26P0206319</vin>
			<description>Livan-суббренд GEELY, это значит, что схема производства, цепочка поставки компонентов, стандарты и уровень качества продукции высшего уровня.
Автомобиль пpедставлeн официaльным дилером Livan в г. Самара В нашем автосалоне для вас: Большой выбор автомобилей Livan в наличии Выгодный обмен по программе Тrаdе-in Большой выбор автомобилей с пробегом Выкуп автомобилей Официальный сервисный центр Кузовной сервис Кредит на выгодных условиях Страхование КАСКО, ОСАГО
Максимальная выгода указана с учетом всех предоставляемых скидок, при условии покупки автомобиля в кредит и  при участии  в программе Тrаdе-in
Авторассрочка:12,24,36 мес. Лизинг (для юридических лиц) Дополнительное оборудование Стоимость указана с учетом скидок и предложений Мы рады видеть Вас ежедневно с 08:00 до 20:00 по адресу: Самара, Ново-Урицкая 22А.</description>
			<images>
				<image>https://cars.avto-provereno.ru/feeds//LLV2C3B26P0206319/6431f8aebc8547174443234c1a046eae.jpg</image>
				<image>https://cars.avto-provereno.ru/feeds//LLV2C3B26P0206319/46d3ac5c2c857d4d24e539b2706462c7.jpg</image>
				<image>https://cars.avto-provereno.ru/feeds//LLV2C3B26P0206319/dc3306b6c5c4a16d2ace0e0889dca72b.jpg</image>
				<image>https://cars.avto-provereno.ru/feeds//LLV2C3B26P0206319/9120267523729b4ce9a4b120b18641fd.jpg</image>
				<image>https://cars.avto-provereno.ru/feeds//LLV2C3B26P0206319/d7c7b610a1d91ab92411229567d9b98c.jpg</image>
				<image>https://cars.avto-provereno.ru/feeds//LLV2C3B26P0206319/a3723ed09e2efa44f86a2dcd8ffd0271.jpg</image>
				<image>https://cars.avto-provereno.ru/feeds//LLV2C3B26P0206319/c1c9b3547f50f6e69a0c4463093d5830.jpg</image>
				<image>https://cars.avto-provereno.ru/feeds//LLV2C3B26P0206319/ce083dd09e37a3f2cea82944e6c931fb.jpg</image>
				<image>https://cars.avto-provereno.ru/feeds//LLV2C3B26P0206319/82612824907eea41eb27d0d32007b3a9.jpg</image>
				<image>https://cars.avto-provereno.ru/feeds//LLV2C3B26P0206319/efb0f421994a6ca990f2afd3934149e2.jpg</image>
				<image>https://cars.avto-provereno.ru/feeds//LLV2C3B26P0206319/b90854187c9b422251989985e6410d46.jpg</image>
				<image>https://cars.avto-provereno.ru/feeds//LLV2C3B26P0206319/77e53cfd5e8a2db5347db8d21e60931f.jpg</image>
				<image>https://cars.avto-provereno.ru/feeds//LLV2C3B26P0206319/d167f404b045d907d4005854735ab18b.jpg</image>
				<image>https://cars.avto-provereno.ru/feeds//LLV2C3B26P0206319/d53151b8be0bb7c74e9ea7d26432e039.jpg</image>
			</images>
		<max_discount>420000</max_discount><priceWithDiscount>1479900</priceWithDiscount><sale_price>1479900</sale_price><url>https://livan-samara.ru/cars/livan-x3-pro-15-cvt-103-лс-luxury-бежевый-2023/</url></car>
		<car>
			<mark_id>Livan</mark_id>
			<folder_id>X3 Pro</folder_id>
			<modification_id>1.5 CVT (103 л.с.)</modification_id>
			<body_type>Внедорожник 5 дв.</body_type>
			<complectation_name>Luxury</complectation_name>
			<wheel>левый</wheel>
			<color>БЕЖЕВЫЙ</color>
			<metallic>да</metallic>
			<availability>в наличии</availability>
			<custom>растаможен</custom>
			<owners_number>Не было владельцев</owners_number>
			<year>2023</year>
			<price>1899900</price>
			<credit_discount>120000</credit_discount>
			<insurance_discount>0</insurance_discount>
			<tradein_discount>100000</tradein_discount>
			<optional_discount>0</optional_discount>
			<currency>RUR</currency>
			<registry_year>2023</registry_year>
			<vin>LLV2C3B28P0206337</vin>
			<description>Livan-суббренд GEELY, это значит, что схема производства, цепочка поставки компонентов, стандарты и уровень качества продукции высшего уровня.
Автомобиль пpедставлeн официaльным дилером Livan в г. Самара В нашем автосалоне для вас: Большой выбор автомобилей Livan в наличии Выгодный обмен по программе Тrаdе-in Большой выбор автомобилей с пробегом Выкуп автомобилей Официальный сервисный центр Кузовной сервис Кредит на выгодных условиях Страхование КАСКО, ОСАГО
Максимальная выгода указана с учетом всех предоставляемых скидок, при условии покупки автомобиля в кредит и  при участии  в программе Тrаdе-in
Авторассрочка:12,24,36 мес. Лизинг (для юридических лиц) Дополнительное оборудование Стоимость указана с учетом скидок и предложений Мы рады видеть Вас ежедневно с 08:00 до 20:00 по адресу: Самара, Ново-Урицкая 22А.</description>
			<images>
				<image>https://cars.avto-provereno.ru/feeds//LLV2C3B28P0206337/9df342d15d18b55d7dec870c621d0f57.jpg</image>
				<image>https://cars.avto-provereno.ru/feeds//LLV2C3B28P0206337/8930c815dc554a1002c5cc124edef742.jpg</image>
				<image>https://cars.avto-provereno.ru/feeds//LLV2C3B28P0206337/e030db4c7a99dafaec6499b1c7327cc8.jpg</image>
				<image>https://cars.avto-provereno.ru/feeds//LLV2C3B28P0206337/cdaed880d82c303b82fa8771f551816a.jpg</image>
				<image>https://cars.avto-provereno.ru/feeds//LLV2C3B28P0206337/2160e85ee03c5537b954ae1dd4a11cac.jpg</image>
				<image>https://cars.avto-provereno.ru/feeds//LLV2C3B28P0206337/8501b77ca90d1906f2cf11909b1fee4a.jpg</image>
				<image>https://cars.avto-provereno.ru/feeds//LLV2C3B28P0206337/00e6da4b5065247348d160f50550a0e6.jpg</image>
				<image>https://cars.avto-provereno.ru/feeds//LLV2C3B28P0206337/2da3fe27b72faa9feef4055937a8a1bd.jpg</image>
				<image>https://cars.avto-provereno.ru/feeds//LLV2C3B28P0206337/194ee58af336522c27bbe0b82f168f82.jpg</image>
				<image>https://cars.avto-provereno.ru/feeds//LLV2C3B28P0206337/de051dfafff6885ba00039547dc073bc.jpg</image>
				<image>https://cars.avto-provereno.ru/feeds//LLV2C3B28P0206337/7ce0f7b0bbe7ba2e8a98364ac9b2926b.jpg</image>
				<image>https://cars.avto-provereno.ru/feeds//LLV2C3B28P0206337/b405387abac9f7961591f2db1e4ffdc6.jpg</image>
				<image>https://cars.avto-provereno.ru/feeds//LLV2C3B28P0206337/74806cfed34378f753d4a545ce321a0e.jpg</image>
				<image>https://cars.avto-provereno.ru/feeds//LLV2C3B28P0206337/8284f06ccabab8d63b712566bc842f6d.jpg</image>
				<image>https://cars.avto-provereno.ru/feeds//LLV2C3B28P0206337/c6631ef65899d86b05f1d3504929753b.jpg</image>
			</images>
		<max_discount>420000</max_discount><priceWithDiscount>1479900</priceWithDiscount><sale_price>1479900</sale_price><url>https://livan-samara.ru/cars/livan-x3-pro-15-cvt-103-лс-luxury-бежевый-2023/</url></car>
		<car>
			<mark_id>Livan</mark_id>
			<folder_id>X3 Pro</folder_id>
			<modification_id>1.5 CVT (103 л.с.)</modification_id>
			<body_type>Внедорожник 5 дв.</body_type>
			<complectation_name>Luxury</complectation_name>
			<wheel>левый</wheel>
			<color>БЕЛЫЙ</color>
			<metallic>нет</metallic>
			<availability>в наличии</availability>
			<custom>растаможен</custom>
			<owners_number>Не было владельцев</owners_number>
			<year>2023</year>
			<price>1889900</price>
			<credit_discount>120000</credit_discount>
			<insurance_discount>0</insurance_discount>
			<tradein_discount>100000</tradein_discount>
			<optional_discount>0</optional_discount>
			<currency>RUR</currency>
			<registry_year>2023</registry_year>
			<vin>LLV2C3B23P0203443</vin>
			<description>Livan-суббренд GEELY, это значит, что схема производства, цепочка поставки компонентов, стандарты и уровень качества продукции высшего уровня.
Автомобиль пpедставлeн официaльным дилером Livan в г. Самара В нашем автосалоне для вас: Большой выбор автомобилей Livan в наличии Выгодный обмен по программе Тrаdе-in Большой выбор автомобилей с пробегом Выкуп автомобилей Официальный сервисный центр Кузовной сервис Кредит на выгодных условиях Страхование КАСКО, ОСАГО
Максимальная выгода указана с учетом всех предоставляемых скидок, при условии покупки автомобиля в кредит и  при участии  в программе Тrаdе-in
Авторассрочка:12,24,36 мес. Лизинг (для юридических лиц) Дополнительное оборудование Стоимость указана с учетом скидок и предложений Мы рады видеть Вас ежедневно с 08:00 до 20:00 по адресу: Самара, Ново-Урицкая 22А.</description>
			<images>
				<image>https://cars.avto-provereno.ru/feeds//LLV2C3B23P0203443/536a4b548c3592518ec2266b870d802a.jpg</image>
				<image>https://cars.avto-provereno.ru/feeds//LLV2C3B23P0203443/6890442c7382007a7ddccb827d44138c.jpg</image>
				<image>https://cars.avto-provereno.ru/feeds//LLV2C3B23P0203443/57eaca298324c80efc706445f635f613.jpg</image>
				<image>https://cars.avto-provereno.ru/feeds//LLV2C3B23P0203443/7d285ca86d3cf348a927ee64d140b9f2.jpg</image>
				<image>https://cars.avto-provereno.ru/feeds//LLV2C3B23P0203443/d8861225a7c2f9565eae41c3ac7b763f.jpg</image>
				<image>https://cars.avto-provereno.ru/feeds//LLV2C3B23P0203443/ff8497d5f830c74de1ec2df03e6272dd.jpg</image>
				<image>https://cars.avto-provereno.ru/feeds//LLV2C3B23P0203443/a1bade0018dd45c84369623846e6e48c.jpg</image>
				<image>https://cars.avto-provereno.ru/feeds//LLV2C3B23P0203443/fc33dbb134f783e1e5d0de3c0ba321b0.jpg</image>
				<image>https://cars.avto-provereno.ru/feeds//LLV2C3B23P0203443/3bc0ea5f79ff0655e53a1deebbf3692a.jpg</image>
				<image>https://cars.avto-provereno.ru/feeds//LLV2C3B23P0203443/58cc2c38ce51c3cb2bd9906c49445b22.jpg</image>
				<image>https://cars.avto-provereno.ru/feeds//LLV2C3B23P0203443/c052f2a87497db914474078d74488c92.jpg</image>
				<image>https://cars.avto-provereno.ru/feeds//LLV2C3B23P0203443/e8010bf74db4b66349a3a70532c03cdb.jpg</image>
				<image>https://cars.avto-provereno.ru/feeds//LLV2C3B23P0203443/2dd029150031343403c6d66361b96494.jpg</image>
			</images>
		<max_discount>420000</max_discount><priceWithDiscount>1469900</priceWithDiscount><sale_price>1469900</sale_price><url>https://livan-samara.ru/cars/livan-x3-pro-15-cvt-103-лс-luxury-белый-2023/</url></car>
		<car>
			<mark_id>Livan</mark_id>
			<folder_id>X3 Pro</folder_id>
			<modification_id>1.5 CVT (103 л.с.)</modification_id>
			<body_type>Внедорожник 5 дв.</body_type>
			<complectation_name>Luxury</complectation_name>
			<wheel>левый</wheel>
			<color>красный</color>
			<metallic>нет</metallic>
			<availability>в наличии</availability>
			<custom>растаможен</custom>
			<owners_number>Не было владельцев</owners_number>
			<year>2023</year>
			<price>1889900</price>
			<credit_discount>120000</credit_discount>
			<insurance_discount>0</insurance_discount>
			<tradein_discount>100000</tradein_discount>
			<optional_discount>0</optional_discount>
			<currency>RUR</currency>
			<registry_year>2023</registry_year>
			<vin>LLV2C3B2XP0205531</vin>
			<description>Livan-суббренд GEELY, это значит, что схема производства, цепочка поставки компонентов, стандарты и уровень качества продукции высшего уровня.
Автомобиль пpедставлeн официaльным дилером Livan в г. Самара В нашем автосалоне для вас: Большой выбор автомобилей Livan в наличии Выгодный обмен по программе Тrаdе-in Большой выбор автомобилей с пробегом Выкуп автомобилей Официальный сервисный центр Кузовной сервис Кредит на выгодных условиях Страхование КАСКО, ОСАГО
Максимальная выгода указана с учетом всех предоставляемых скидок, при условии покупки автомобиля в кредит и  при участии  в программе Тrаdе-in
Авторассрочка:12,24,36 мес. Лизинг (для юридических лиц) Дополнительное оборудование Стоимость указана с учетом скидок и предложений Мы рады видеть Вас ежедневно с 08:00 до 20:00 по адресу: Самара, Ново-Урицкая 22А.</description>
			<images>
				<image>https://cars.avto-provereno.ru/feeds//LLV2C3B2XP0205531/cd3ae91003652df79f35a53224e82cd0.jpg</image>
				<image>https://cars.avto-provereno.ru/feeds//LLV2C3B2XP0205531/a005194864cc89d7eae447af80555e8d.jpg</image>
				<image>https://cars.avto-provereno.ru/feeds//LLV2C3B2XP0205531/86c0f2707856ab6584b9743eb2743cc7.jpg</image>
				<image>https://cars.avto-provereno.ru/feeds//LLV2C3B2XP0205531/303a538d761247527df6c5b4b6cb00f5.jpg</image>
				<image>https://cars.avto-provereno.ru/feeds//LLV2C3B2XP0205531/9ad8268c6e048c0b9dea0c3969a315e4.jpg</image>
				<image>https://cars.avto-provereno.ru/feeds//LLV2C3B2XP0205531/4f78c26f32a5d2b3188d78091c7e6674.jpg</image>
				<image>https://cars.avto-provereno.ru/feeds//LLV2C3B2XP0205531/90149dfbd9a23a56fe00c85811c848a2.jpg</image>
				<image>https://cars.avto-provereno.ru/feeds//LLV2C3B2XP0205531/8b471415fa171ff243a4cf6901f5d756.jpg</image>
				<image>https://cars.avto-provereno.ru/feeds//LLV2C3B2XP0205531/3bcc58982550f2322f225f49567d649f.jpg</image>
				<image>https://cars.avto-provereno.ru/feeds//LLV2C3B2XP0205531/f5f932d8e7507730faa36e8f5f91ddd9.jpg</image>
			</images>
		<max_discount>420000</max_discount><priceWithDiscount>1469900</priceWithDiscount><sale_price>1469900</sale_price><url>https://livan-samara.ru/cars/livan-x3-pro-15-cvt-103-лс-luxury-красный-2023/</url></car>
		<car>
			<mark_id>Livan</mark_id>
			<folder_id>X3 Pro</folder_id>
			<modification_id>1.5 CVT (103 л.с.)</modification_id>
			<body_type>Внедорожник 5 дв.</body_type>
			<complectation_name>Luxury</complectation_name>
			<wheel>левый</wheel>
			<color>СИНИЙ</color>
			<metallic>нет</metallic>
			<availability>в наличии</availability>
			<custom>растаможен</custom>
			<owners_number>Не было владельцев</owners_number>
			<year>2023</year>
			<price>1899900</price>
			<credit_discount>120000</credit_discount>
			<insurance_discount>0</insurance_discount>
			<tradein_discount>100000</tradein_discount>
			<optional_discount>0</optional_discount>
			<currency>RUR</currency>
			<registry_year>2023</registry_year>
			<vin>LLV2C3B22P0205555</vin>
			<description>Livan-суббренд GEELY, это значит, что схема производства, цепочка поставки компонентов, стандарты и уровень качества продукции высшего уровня.
Автомобиль пpедставлeн официaльным дилером Livan в г. Самара В нашем автосалоне для вас: Большой выбор автомобилей Livan в наличии Выгодный обмен по программе Тrаdе-in Большой выбор автомобилей с пробегом Выкуп автомобилей Официальный сервисный центр Кузовной сервис Кредит на выгодных условиях Страхование КАСКО, ОСАГО
Максимальная выгода указана с учетом всех предоставляемых скидок, при условии покупки автомобиля в кредит и  при участии  в программе Тrаdе-in
Авторассрочка:12,24,36 мес. Лизинг (для юридических лиц) Дополнительное оборудование Стоимость указана с учетом скидок и предложений Мы рады видеть Вас ежедневно с 08:00 до 20:00 по адресу: Самара, Ново-Урицкая 22А.</description>
			<images>
				<image>https://cars.avto-provereno.ru/feeds//LLV2C3B22P0205555/f3971ec920e0750c07bff00af7f1f28e.jpg</image>
				<image>https://cars.avto-provereno.ru/feeds//LLV2C3B22P0205555/962aec3e64c7aef9692e641614a6d8b1.jpg</image>
				<image>https://cars.avto-provereno.ru/feeds//LLV2C3B22P0205555/5b7d05b7476cc4198d759e8e60625632.jpg</image>
				<image>https://cars.avto-provereno.ru/feeds//LLV2C3B22P0205555/93d25cd5c9f6498e5202c2bbb15d0c8e.jpg</image>
				<image>https://cars.avto-provereno.ru/feeds//LLV2C3B22P0205555/92b7181fc8d66ce175ac601f9a991af3.jpg</image>
				<image>https://cars.avto-provereno.ru/feeds//LLV2C3B22P0205555/667f8ba79171a96436bb338c0aa54c87.jpg</image>
				<image>https://cars.avto-provereno.ru/feeds//LLV2C3B22P0205555/a40afae43d48d0e01e573c94116e13b6.jpg</image>
				<image>https://cars.avto-provereno.ru/feeds//LLV2C3B22P0205555/78c62f4291b1c875b9401906883e49a5.jpg</image>
				<image>https://cars.avto-provereno.ru/feeds//LLV2C3B22P0205555/843473959e8090ab7a0453d966941b7a.jpg</image>
				<image>https://cars.avto-provereno.ru/feeds//LLV2C3B22P0205555/9785bfb1ce5e65248b47d782750866f9.jpg</image>
				<image>https://cars.avto-provereno.ru/feeds//LLV2C3B22P0205555/1f785e3e6984885b58fa5a73a9bc65a9.jpg</image>
			</images>
		<max_discount>420000</max_discount><priceWithDiscount>1479900</priceWithDiscount><sale_price>1479900</sale_price><url>https://livan-samara.ru/cars/livan-x3-pro-15-cvt-103-лс-luxury-синий-2023/</url></car>
		<car>
			<mark_id>Livan</mark_id>
			<folder_id>X3 Pro</folder_id>
			<modification_id>1.5 CVT (103 л.с.)</modification_id>
			<body_type>Внедорожник 5 дв.</body_type>
			<complectation_name>Luxury</complectation_name>
			<wheel>левый</wheel>
			<color>СИНИЙ</color>
			<metallic>нет</metallic>
			<availability>в наличии</availability>
			<custom>растаможен</custom>
			<owners_number>Не было владельцев</owners_number>
			<year>2023</year>
			<price>1899900</price>
			<credit_discount>120000</credit_discount>
			<insurance_discount>0</insurance_discount>
			<tradein_discount>100000</tradein_discount>
			<optional_discount>0</optional_discount>
			<currency>RUR</currency>
			<registry_year>2023</registry_year>
			<vin>LLV2C3B26P0205591</vin>
			<description>Livan-суббренд GEELY, это значит, что схема производства, цепочка поставки компонентов, стандарты и уровень качества продукции высшего уровня.
Автомобиль пpедставлeн официaльным дилером Livan в г. Самара В нашем автосалоне для вас: Большой выбор автомобилей Livan в наличии Выгодный обмен по программе Тrаdе-in Большой выбор автомобилей с пробегом Выкуп автомобилей Официальный сервисный центр Кузовной сервис Кредит на выгодных условиях Страхование КАСКО, ОСАГО
Максимальная выгода указана с учетом всех предоставляемых скидок, при условии покупки автомобиля в кредит и  при участии  в программе Тrаdе-in
Авторассрочка:12,24,36 мес. Лизинг (для юридических лиц) Дополнительное оборудование Стоимость указана с учетом скидок и предложений Мы рады видеть Вас ежедневно с 08:00 до 20:00 по адресу: Самара, Ново-Урицкая 22А.</description>
			<images>
				<image>https://cars.avto-provereno.ru/feeds//LLV2C3B26P0205591/a0c3f7798073bbda62de517ad01cb4b0.jpg</image>
				<image>https://cars.avto-provereno.ru/feeds//LLV2C3B26P0205591/368e4ceebc0502d612cf780f2e18fbe5.jpg</image>
				<image>https://cars.avto-provereno.ru/feeds//LLV2C3B26P0205591/59945ada69258da3c6752ff5467b6aee.jpg</image>
				<image>https://cars.avto-provereno.ru/feeds//LLV2C3B26P0205591/a40ffdd8ae3d5f33a6aded7a618ff630.jpg</image>
				<image>https://cars.avto-provereno.ru/feeds//LLV2C3B26P0205591/094e590705cc4733f2b0c73d02d6c22c.jpg</image>
				<image>https://cars.avto-provereno.ru/feeds//LLV2C3B26P0205591/c818a32b281bff1cd13bda21bb667e21.jpg</image>
				<image>https://cars.avto-provereno.ru/feeds//LLV2C3B26P0205591/d8e43f835b4b7bcc87d0f87e45dc9975.jpg</image>
				<image>https://cars.avto-provereno.ru/feeds//LLV2C3B26P0205591/cee5da91014897edd5fdfe80d11ccb81.jpg</image>
				<image>https://cars.avto-provereno.ru/feeds//LLV2C3B26P0205591/dc357d7ee535310224d4019516129e22.jpg</image>
				<image>https://cars.avto-provereno.ru/feeds//LLV2C3B26P0205591/82899994e067c16c22bc0606f8125683.jpg</image>
			</images>
		<max_discount>420000</max_discount><priceWithDiscount>1479900</priceWithDiscount><sale_price>1479900</sale_price><url>https://livan-samara.ru/cars/livan-x3-pro-15-cvt-103-лс-luxury-синий-2023/</url></car>
		<car>
			<mark_id>Livan</mark_id>
			<folder_id>X6 Pro</folder_id>
			<modification_id>1.5 AMT (147 л.с.)</modification_id>
			<body_type>Внедорожник 5 дв.</body_type>
			<complectation_name>Premium</complectation_name>
			<wheel>левый</wheel>
			<color>БЕЛЫЙ</color>
			<metallic>нет</metallic>
			<availability>в наличии</availability>
			<custom>растаможен</custom>
			<owners_number>Не было владельцев</owners_number>
			<year>2023</year>
			<price>2739900</price>
			<credit_discount>0</credit_discount>
			<insurance_discount>0</insurance_discount>
			<tradein_discount>165000</tradein_discount>
			<optional_discount>0</optional_discount>
			<currency>RUR</currency>
			<registry_year>2023</registry_year>
			<vin>LLV5C3B2XP0500626</vin>
			<description>Livan-суббренд GEELY, это значит, что схема производства, цепочка поставки компонентов, стандарты и уровень качества продукции высшего уровня.
Автомобиль пpедставлeн официaльным дилером Livan в г. Самара В нашем автосалоне для вас: Большой выбор автомобилей Livan в наличии Выгодный обмен по программе Тrаdе-in Большой выбор автомобилей с пробегом Выкуп автомобилей Официальный сервисный центр Кузовной сервис Кредит на выгодных условиях Страхование КАСКО, ОСАГО
Максимальная выгода указана с учетом всех предоставляемых скидок, при условии покупки автомобиля в кредит и  при участии  в программе Тrаdе-in
Авторассрочка:12,24,36 мес. Лизинг (для юридических лиц) Дополнительное оборудование Стоимость указана с учетом скидок и предложений Мы рады видеть Вас ежедневно с 08:00 до 20:00 по адресу: Самара, Ново-Урицкая 22А.</description>
			<images>
				<image>https://cars.avto-provereno.ru/feeds//LLV5C3B2XP0500626/55c13b25c1096276fcf3254a7761169b.jpg</image>
				<image>https://cars.avto-provereno.ru/feeds//LLV5C3B2XP0500626/6b7176bde1708d255cd3b442618d0f96.jpg</image>
				<image>https://cars.avto-provereno.ru/feeds//LLV5C3B2XP0500626/c3f034366344753c5a93941b816c6c5e.jpg</image>
				<image>https://cars.avto-provereno.ru/feeds//LLV5C3B2XP0500626/161225c0cac62100ce3dd2ecd8069942.jpg</image>
				<image>https://cars.avto-provereno.ru/feeds//LLV5C3B2XP0500626/fc54e92a32d3a304a333e3a55f5b132e.jpg</image>
				<image>https://cars.avto-provereno.ru/feeds//LLV5C3B2XP0500626/63fc08120c3401547fcabd2e9088353b.jpg</image>
				<image>https://cars.avto-provereno.ru/feeds//LLV5C3B2XP0500626/dc9888568bccc943787d88cceb47894a.jpg</image>
				<image>https://cars.avto-provereno.ru/feeds//LLV5C3B2XP0500626/e71189601cac8a319f5de05f9fc0cd7d.jpg</image>
				<image>https://cars.avto-provereno.ru/feeds//LLV5C3B2XP0500626/df6f9e82911e3d33f4fe8459aa653682.jpg</image>
			</images>
		<max_discount>799900</max_discount><priceWithDiscount>1940000</priceWithDiscount><sale_price>1940000</sale_price><url>https://livan-samara.ru/cars/livan-x6-pro-15-amt-147-лс-premium-белый-2023/</url></car>
		<car>
			<mark_id>Livan</mark_id>
			<folder_id>X6 Pro</folder_id>
			<modification_id>1.5 AMT (147 л.с.)</modification_id>
			<body_type>Внедорожник 5 дв.</body_type>
			<complectation_name>Premium</complectation_name>
			<wheel>левый</wheel>
			<color>БЕЛЫЙ</color>
			<metallic>нет</metallic>
			<availability>в наличии</availability>
			<custom>растаможен</custom>
			<owners_number>Не было владельцев</owners_number>
			<year>2023</year>
			<price>2739900</price>
			<credit_discount>0</credit_discount>
			<insurance_discount>0</insurance_discount>
			<tradein_discount>165000</tradein_discount>
			<optional_discount>0</optional_discount>
			<currency>RUR</currency>
			<registry_year>2023</registry_year>
			<vin>LLV5C3B29P0500780</vin>
			<description>Livan-суббренд GEELY, это значит, что схема производства, цепочка поставки компонентов, стандарты и уровень качества продукции высшего уровня.
Автомобиль пpедставлeн официaльным дилером Livan в г. Самара В нашем автосалоне для вас: Большой выбор автомобилей Livan в наличии Выгодный обмен по программе Тrаdе-in Большой выбор автомобилей с пробегом Выкуп автомобилей Официальный сервисный центр Кузовной сервис Кредит на выгодных условиях Страхование КАСКО, ОСАГО
Максимальная выгода указана с учетом всех предоставляемых скидок, при условии покупки автомобиля в кредит и  при участии  в программе Тrаdе-in
Авторассрочка:12,24,36 мес. Лизинг (для юридических лиц) Дополнительное оборудование Стоимость указана с учетом скидок и предложений Мы рады видеть Вас ежедневно с 08:00 до 20:00 по адресу: Самара, Ново-Урицкая 22А.</description>
			<images>
				<image>https://cars.avto-provereno.ru/feeds//LLV5C3B29P0500780/c01c0ea01073e9900cb7044e3b2c8c91.jpg</image>
				<image>https://cars.avto-provereno.ru/feeds//LLV5C3B29P0500780/16c19bf4b46e74b23fcf75d8939b2b7f.jpg</image>
				<image>https://cars.avto-provereno.ru/feeds//LLV5C3B29P0500780/1c7c8763704df0913146b5479aead7d2.jpg</image>
				<image>https://cars.avto-provereno.ru/feeds//LLV5C3B29P0500780/ba40983bf4d120322d340e49141c2fdc.jpg</image>
				<image>https://cars.avto-provereno.ru/feeds//LLV5C3B29P0500780/bfffe48d44e41f2188aadf3bd26b25e6.jpg</image>
				<image>https://cars.avto-provereno.ru/feeds//LLV5C3B29P0500780/0e24dab99cd534dea3a76cd48d5dd02e.jpg</image>
				<image>https://cars.avto-provereno.ru/feeds//LLV5C3B29P0500780/0e1ac9ff32d5f9f50fd5e15a22bc931d.jpg</image>
				<image>https://cars.avto-provereno.ru/feeds//LLV5C3B29P0500780/326b162134884938872d8a60644b35d8.jpg</image>
				<image>https://cars.avto-provereno.ru/feeds//LLV5C3B29P0500780/e13396742a746aabf301dfdb55cb2b42.jpg</image>
			</images>
		<max_discount>799900</max_discount><priceWithDiscount>1940000</priceWithDiscount><sale_price>1940000</sale_price><url>https://livan-samara.ru/cars/livan-x6-pro-15-amt-147-лс-premium-белый-2023/</url></car>
		<car>
			<mark_id>Livan</mark_id>
			<folder_id>X6 Pro</folder_id>
			<modification_id>1.5 AMT (147 л.с.)</modification_id>
			<body_type>Внедорожник 5 дв.</body_type>
			<complectation_name>Premium</complectation_name>
			<wheel>левый</wheel>
			<color>БЕЛЫЙ</color>
			<metallic>нет</metallic>
			<availability>в наличии</availability>
			<custom>растаможен</custom>
			<owners_number>Не было владельцев</owners_number>
			<year>2023</year>
			<price>2739900</price>
			<credit_discount>0</credit_discount>
			<insurance_discount>0</insurance_discount>
			<tradein_discount>165000</tradein_discount>
			<optional_discount>0</optional_discount>
			<currency>RUR</currency>
			<registry_year>2023</registry_year>
			<vin>LLV5C3B24P0500766</vin>
			<description>Livan-суббренд GEELY, это значит, что схема производства, цепочка поставки компонентов, стандарты и уровень качества продукции высшего уровня.
Автомобиль пpедставлeн официaльным дилером Livan в г. Самара В нашем автосалоне для вас: Большой выбор автомобилей Livan в наличии Выгодный обмен по программе Тrаdе-in Большой выбор автомобилей с пробегом Выкуп автомобилей Официальный сервисный центр Кузовной сервис Кредит на выгодных условиях Страхование КАСКО, ОСАГО
Максимальная выгода указана с учетом всех предоставляемых скидок, при условии покупки автомобиля в кредит и  при участии  в программе Тrаdе-in
Авторассрочка:12,24,36 мес. Лизинг (для юридических лиц) Дополнительное оборудование Стоимость указана с учетом скидок и предложений Мы рады видеть Вас ежедневно с 08:00 до 20:00 по адресу: Самара, Ново-Урицкая 22А.</description>
			<images>
				<image>https://cars.avto-provereno.ru/feeds//LLV5C3B24P0500766/8fd1f52cb5e62cd24822cc290be649e2.jpg</image>
				<image>https://cars.avto-provereno.ru/feeds//LLV5C3B24P0500766/864ad4f08ef1607c5425344ed6e4b3a0.jpg</image>
				<image>https://cars.avto-provereno.ru/feeds//LLV5C3B24P0500766/63f370f0b5732b200abd814e97983ea1.jpg</image>
				<image>https://cars.avto-provereno.ru/feeds//LLV5C3B24P0500766/6c19a516d9f5a18b74a99adaa0c188c3.jpg</image>
				<image>https://cars.avto-provereno.ru/feeds//LLV5C3B24P0500766/a085b184a0836a5ca4e45e6e4e0dca9b.jpg</image>
				<image>https://cars.avto-provereno.ru/feeds//LLV5C3B24P0500766/c878c2b056405f8d9bfef7641ee4ac19.jpg</image>
				<image>https://cars.avto-provereno.ru/feeds//LLV5C3B24P0500766/64790499a788916c0421ca6f7934e8d3.jpg</image>
				<image>https://cars.avto-provereno.ru/feeds//LLV5C3B24P0500766/767b63312bc39def4606b831d92b95b1.jpg</image>
				<image>https://cars.avto-provereno.ru/feeds//LLV5C3B24P0500766/ab3fc21043547dfa2316300c157a3eac.jpg</image>
				<image>https://cars.avto-provereno.ru/feeds//LLV5C3B24P0500766/1c188e9b7cc7b502c57e61c3122e0f9d.jpg</image>
			</images>
		<max_discount>799900</max_discount><priceWithDiscount>1940000</priceWithDiscount><sale_price>1940000</sale_price><url>https://livan-samara.ru/cars/livan-x6-pro-15-amt-147-лс-premium-белый-2023/</url></car>
		<car>
			<mark_id>Livan</mark_id>
			<folder_id>X6 Pro</folder_id>
			<modification_id>1.5 AMT (147 л.с.)</modification_id>
			<body_type>Внедорожник 5 дв.</body_type>
			<complectation_name>Premium</complectation_name>
			<wheel>левый</wheel>
			<color>ЗЕЛЕНЫЙ</color>
			<metallic>нет</metallic>
			<availability>в наличии</availability>
			<custom>растаможен</custom>
			<owners_number>Не было владельцев</owners_number>
			<year>2024</year>
			<price>2749900</price>
			<credit_discount>0</credit_discount>
			<insurance_discount>0</insurance_discount>
			<tradein_discount>165000</tradein_discount>
			<optional_discount>0</optional_discount>
			<currency>RUR</currency>
			<registry_year>2024</registry_year>
			<vin>LLV5C3B22R0501756</vin>
			<description>Livan-суббренд GEELY, это значит, что схема производства, цепочка поставки компонентов, стандарты и уровень качества продукции высшего уровня.
Автомобиль пpедставлeн официaльным дилером Livan в г. Самара В нашем автосалоне для вас: Большой выбор автомобилей Livan в наличии Выгодный обмен по программе Тrаdе-in Большой выбор автомобилей с пробегом Выкуп автомобилей Официальный сервисный центр Кузовной сервис Кредит на выгодных условиях Страхование КАСКО, ОСАГО
Максимальная выгода указана с учетом всех предоставляемых скидок, при условии покупки автомобиля в кредит и  при участии  в программе Тrаdе-in
Авторассрочка:12,24,36 мес. Лизинг (для юридических лиц) Дополнительное оборудование Стоимость указана с учетом скидок и предложений Мы рады видеть Вас ежедневно с 08:00 до 20:00 по адресу: Самара, Ново-Урицкая 22А.</description>
			<images>
				<image>https://cars.avto-provereno.ru/feeds//LLV5C3B22R0501756/8cba4fd1b70c1dc2d0e2ab07c9c37bdf.jpg</image>
				<image>https://cars.avto-provereno.ru/feeds//LLV5C3B22R0501756/9b0e3246d11a0d9f708a1db3d8a2fe7d.jpg</image>
				<image>https://cars.avto-provereno.ru/feeds//LLV5C3B22R0501756/410f7687d55c17242a9a68609b6d698b.jpg</image>
				<image>https://cars.avto-provereno.ru/feeds//LLV5C3B22R0501756/e366f77526ff9959d657ae0a77063cdd.jpg</image>
				<image>https://cars.avto-provereno.ru/feeds//LLV5C3B22R0501756/726ed9d2eb2230a1f859e2885b273a6e.jpg</image>
				<image>https://cars.avto-provereno.ru/feeds//LLV5C3B22R0501756/d0eedc2612ee91a7cd8e136c5e162c69.jpg</image>
				<image>https://cars.avto-provereno.ru/feeds//LLV5C3B22R0501756/14cc4342465b408fb1c00701038fd08b.jpg</image>
				<image>https://cars.avto-provereno.ru/feeds//LLV5C3B22R0501756/0bdf7991677ea7ee59670e368ed61c70.jpg</image>
				<image>https://cars.avto-provereno.ru/feeds//LLV5C3B22R0501756/fec3f40b40da9b935c57fa53ee6d7a0c.jpg</image>
				<image>https://cars.avto-provereno.ru/feeds//LLV5C3B22R0501756/63c423517fa88f2948d073001378b313.jpg</image>
				<image>https://cars.avto-provereno.ru/feeds//LLV5C3B22R0501756/319edbeeffd42c59ef81f71f44f10104.jpg</image>
				<image>https://cars.avto-provereno.ru/feeds//LLV5C3B22R0501756/cd341b843366cda4a4fe9c445db975ce.jpg</image>
				<image>https://cars.avto-provereno.ru/feeds//LLV5C3B22R0501756/eb7b367c109a7d2476b27d6f50cdb3cf.jpg</image>
			</images>
		<max_discount>659900</max_discount><priceWithDiscount>2090000</priceWithDiscount><sale_price>2090000</sale_price><url>https://livan-samara.ru/cars/livan-x6-pro-15-amt-147-лс-premium-зеленый-2024/</url></car>
		<car>
			<mark_id>Livan</mark_id>
			<folder_id>X6 Pro</folder_id>
			<modification_id>1.5 AMT (147 л.с.)</modification_id>
			<body_type>Внедорожник 5 дв.</body_type>
			<complectation_name>Premium</complectation_name>
			<wheel>левый</wheel>
			<color>Серый</color>
			<metallic>нет</metallic>
			<availability>в наличии</availability>
			<custom>растаможен</custom>
			<owners_number>Не было владельцев</owners_number>
			<year>2023</year>
			<price>2749900</price>
			<credit_discount>0</credit_discount>
			<insurance_discount>0</insurance_discount>
			<tradein_discount>165000</tradein_discount>
			<optional_discount>0</optional_discount>
			<currency>RUR</currency>
			<registry_year>2023</registry_year>
			<vin>LLV5C3B28P0501242</vin>
			<description>Livan-суббренд GEELY, это значит, что схема производства, цепочка поставки компонентов, стандарты и уровень качества продукции высшего уровня.
Автомобиль пpедставлeн официaльным дилером Livan в г. Самара В нашем автосалоне для вас: Большой выбор автомобилей Livan в наличии Выгодный обмен по программе Тrаdе-in Большой выбор автомобилей с пробегом Выкуп автомобилей Официальный сервисный центр Кузовной сервис Кредит на выгодных условиях Страхование КАСКО, ОСАГО
Максимальная выгода указана с учетом всех предоставляемых скидок, при условии покупки автомобиля в кредит и  при участии  в программе Тrаdе-in
Авторассрочка:12,24,36 мес. Лизинг (для юридических лиц) Дополнительное оборудование Стоимость указана с учетом скидок и предложений Мы рады видеть Вас ежедневно с 08:00 до 20:00 по адресу: Самара, Ново-Урицкая 22А.</description>
			<images>
				<image>https://cars.avto-provereno.ru/feeds//LLV5C3B28P0501242/162210b5e9e55286d1f101134ba09482.jpg</image>
				<image>https://cars.avto-provereno.ru/feeds//LLV5C3B28P0501242/da8012ed60f4f8f1a189dcfad7706ede.jpg</image>
				<image>https://cars.avto-provereno.ru/feeds//LLV5C3B28P0501242/f751427c0ba74f55e94679818bf78e84.jpg</image>
				<image>https://cars.avto-provereno.ru/feeds//LLV5C3B28P0501242/3bb0826bc7f813241dcc46bda137ccca.jpg</image>
				<image>https://cars.avto-provereno.ru/feeds//LLV5C3B28P0501242/0ebd9a6d2b5fd0e6dcde087af9455f9c.jpg</image>
				<image>https://cars.avto-provereno.ru/feeds//LLV5C3B28P0501242/11d80c80b210a17745f1765a3de9b1e4.jpg</image>
				<image>https://cars.avto-provereno.ru/feeds//LLV5C3B28P0501242/60c732a14b9fa4381ab92b37c9c970c8.jpg</image>
				<image>https://cars.avto-provereno.ru/feeds//LLV5C3B28P0501242/c8c8f13822392cd8963a7e8e165284bb.jpg</image>
				<image>https://cars.avto-provereno.ru/feeds//LLV5C3B28P0501242/eb520ad2ee2470f7bd094deaf7195e0f.jpg</image>
			</images>
		<max_discount>799900</max_discount><priceWithDiscount>1950000</priceWithDiscount><sale_price>1950000</sale_price><url>https://livan-samara.ru/cars/livan-x6-pro-15-amt-147-лс-premium-серый-2023/</url></car>
		<car>
			<mark_id>Livan</mark_id>
			<folder_id>X6 Pro</folder_id>
			<modification_id>1.5 AMT (147 л.с.)</modification_id>
			<body_type>Внедорожник 5 дв.</body_type>
			<complectation_name>Premium</complectation_name>
			<wheel>левый</wheel>
			<color>Серый</color>
			<metallic>нет</metallic>
			<availability>в наличии</availability>
			<custom>растаможен</custom>
			<owners_number>Не было владельцев</owners_number>
			<year>2023</year>
			<price>2749900</price>
			<credit_discount>0</credit_discount>
			<insurance_discount>0</insurance_discount>
			<tradein_discount>165000</tradein_discount>
			<optional_discount>0</optional_discount>
			<currency>RUR</currency>
			<registry_year>2023</registry_year>
			<vin>LLV5C3B25P0501246</vin>
			<description>Livan-суббренд GEELY, это значит, что схема производства, цепочка поставки компонентов, стандарты и уровень качества продукции высшего уровня.
Автомобиль пpедставлeн официaльным дилером Livan в г. Самара В нашем автосалоне для вас: Большой выбор автомобилей Livan в наличии Выгодный обмен по программе Тrаdе-in Большой выбор автомобилей с пробегом Выкуп автомобилей Официальный сервисный центр Кузовной сервис Кредит на выгодных условиях Страхование КАСКО, ОСАГО
Максимальная выгода указана с учетом всех предоставляемых скидок, при условии покупки автомобиля в кредит и  при участии  в программе Тrаdе-in
Авторассрочка:12,24,36 мес. Лизинг (для юридических лиц) Дополнительное оборудование Стоимость указана с учетом скидок и предложений Мы рады видеть Вас ежедневно с 08:00 до 20:00 по адресу: Самара, Ново-Урицкая 22А.</description>
			<images>
				<image>https://cars.avto-provereno.ru/feeds//LLV5C3B25P0501246/60a7135591f5557e5a613fa252cad9b2.jpg</image>
				<image>https://cars.avto-provereno.ru/feeds//LLV5C3B25P0501246/29e51d289b03bd2f09cd53a0f80b4690.jpg</image>
				<image>https://cars.avto-provereno.ru/feeds//LLV5C3B25P0501246/4c76869ae8b5e72d925e5a9280fe8701.jpg</image>
				<image>https://cars.avto-provereno.ru/feeds//LLV5C3B25P0501246/2803bc74e11ca65ddeba3ee6ea1437c5.jpg</image>
				<image>https://cars.avto-provereno.ru/feeds//LLV5C3B25P0501246/0ac8747a791098e5f179a832b64fe047.jpg</image>
				<image>https://cars.avto-provereno.ru/feeds//LLV5C3B25P0501246/a6b3a884b075a3953ef92291f4449ae3.jpg</image>
				<image>https://cars.avto-provereno.ru/feeds//LLV5C3B25P0501246/2d2bb92c06309351ddee72532f2c6693.jpg</image>
				<image>https://cars.avto-provereno.ru/feeds//LLV5C3B25P0501246/6342aad3b28fdd4a2ea65e3103a8d401.jpg</image>
			</images>
		<max_discount>799900</max_discount><priceWithDiscount>1950000</priceWithDiscount><sale_price>1950000</sale_price><url>https://livan-samara.ru/cars/livan-x6-pro-15-amt-147-лс-premium-серый-2023/</url></car>
		<car>
			<mark_id>Livan</mark_id>
			<folder_id>X6 Pro</folder_id>
			<modification_id>1.5 AMT (147 л.с.)</modification_id>
			<body_type>Внедорожник 5 дв.</body_type>
			<complectation_name>Premium</complectation_name>
			<wheel>левый</wheel>
			<color>Серый</color>
			<metallic>нет</metallic>
			<availability>в наличии</availability>
			<custom>растаможен</custom>
			<owners_number>Не было владельцев</owners_number>
			<year>2023</year>
			<price>2749900</price>
			<credit_discount>0</credit_discount>
			<insurance_discount>0</insurance_discount>
			<tradein_discount>165000</tradein_discount>
			<optional_discount>0</optional_discount>
			<currency>RUR</currency>
			<registry_year>2023</registry_year>
			<vin>LLV5C3B20P0501218</vin>
			<description>Livan-суббренд GEELY, это значит, что схема производства, цепочка поставки компонентов, стандарты и уровень качества продукции высшего уровня.
Автомобиль пpедставлeн официaльным дилером Livan в г. Самара В нашем автосалоне для вас: Большой выбор автомобилей Livan в наличии Выгодный обмен по программе Тrаdе-in Большой выбор автомобилей с пробегом Выкуп автомобилей Официальный сервисный центр Кузовной сервис Кредит на выгодных условиях Страхование КАСКО, ОСАГО
Максимальная выгода указана с учетом всех предоставляемых скидок, при условии покупки автомобиля в кредит и  при участии  в программе Тrаdе-in
Авторассрочка:12,24,36 мес. Лизинг (для юридических лиц) Дополнительное оборудование Стоимость указана с учетом скидок и предложений Мы рады видеть Вас ежедневно с 08:00 до 20:00 по адресу: Самара, Ново-Урицкая 22А.</description>
			<images>
				<image>https://cars.avto-provereno.ru/feeds//LLV5C3B20P0501218/4f73a677fef2280548cfa57e2bedb96a.jpg</image>
				<image>https://cars.avto-provereno.ru/feeds//LLV5C3B20P0501218/6af5eeda7abe94142c19f240d238309d.jpg</image>
				<image>https://cars.avto-provereno.ru/feeds//LLV5C3B20P0501218/90bc1b371dca760e8f8315f4a4819791.jpg</image>
				<image>https://cars.avto-provereno.ru/feeds//LLV5C3B20P0501218/69839329c570cdd681e8c6ace2d4e71d.jpg</image>
				<image>https://cars.avto-provereno.ru/feeds//LLV5C3B20P0501218/9159a2f61b0c5211a7f4c4351e6455e0.jpg</image>
				<image>https://cars.avto-provereno.ru/feeds//LLV5C3B20P0501218/774bd8632ef250d989437c01caf62189.jpg</image>
				<image>https://cars.avto-provereno.ru/feeds//LLV5C3B20P0501218/8a0755fd7ccab7dd3395b74f8008556f.jpg</image>
			</images>
		<max_discount>799900</max_discount><priceWithDiscount>1950000</priceWithDiscount><sale_price>1950000</sale_price><url>https://livan-samara.ru/cars/livan-x6-pro-15-amt-147-лс-premium-серый-2023/</url></car>
	</cars>
</data>